<Class>
  <Function>
    <FunctionName>public string GetXMLName()</FunctionName>
    <NumberOfScopes>0</NumberOfScopes>
    <NumberOfLines>2</NumberOfLines>
  </Function>
  <Function>
    <FunctionName>public void DisplayAnalysisToStandardOutput()</FunctionName>
    <NumberOfScopes>1</NumberOfScopes>
    <NumberOfLines>7</NumberOfLines>
  </Function>
  <Function>
    <FunctionName>public void DisplayAnalysisToXML()</FunctionName>
    <NumberOfScopes>2</NumberOfScopes>
    <NumberOfLines>17</NumberOfLines>
  </Function>
  <Function>
    <FunctionName>public void CreateXMLDocument()</FunctionName>
    <NumberOfScopes>1</NumberOfScopes>
    <NumberOfLines>60</NumberOfLines>
  </Function>
  <Function>
    <FunctionName>private void CreateXMLDocumentUsingXmlWriter()</FunctionName>
    <NumberOfScopes>1</NumberOfScopes>
    <NumberOfLines>80</NumberOfLines>
  </Function>
  <Function>
    <FunctionName>public void DisplayRelationshipsToConsole()</FunctionName>
    <NumberOfScopes>0</NumberOfScopes>
    <NumberOfLines>83</NumberOfLines>
  </Function>
  <Function>
    <FunctionName>public void DisplayRelationshipsToXML()</FunctionName>
    <NumberOfScopes>0</NumberOfScopes>
    <NumberOfLines>86</NumberOfLines>
  </Function>
  <Function>
    <FunctionName>/*private int CountStatements(List&lt;string&gt; lines)</FunctionName>
    <NumberOfScopes>1</NumberOfScopes>
    <NumberOfLines>93</NumberOfLines>
  </Function>
  <Function>
    <FunctionName>static void Main(string[] args)</FunctionName>
    <NumberOfScopes>0</NumberOfScopes>
    <NumberOfLines>95</NumberOfLines>
  </Function>
  <Function>
    <FunctionName>public bool InheritanceExists()</FunctionName>
    <NumberOfScopes>2</NumberOfScopes>
    <NumberOfLines>11</NumberOfLines>
  </Function>
  <Function>
    <FunctionName>public bool AggregationExists()</FunctionName>
    <NumberOfScopes>0</NumberOfScopes>
    <NumberOfLines>13</NumberOfLines>
  </Function>
  <Function>
    <FunctionName>public bool CompositionExists()</FunctionName>
    <NumberOfScopes>0</NumberOfScopes>
    <NumberOfLines>15</NumberOfLines>
  </Function>
  <Function>
    <FunctionName>public bool UsingExists()</FunctionName>
    <NumberOfScopes>0</NumberOfScopes>
    <NumberOfLines>17</NumberOfLines>
  </Function>
  <Function>
    <FunctionName>static void Main(string[] args)</FunctionName>
    <NumberOfScopes>0</NumberOfScopes>
    <NumberOfLines>19</NumberOfLines>
  </Function>
  <Function>
    <FunctionName>public bool IsDirectoryPathTypeAString(string path)</FunctionName>
    <NumberOfScopes>2</NumberOfScopes>
    <NumberOfLines>10</NumberOfLines>
  </Function>
  <Function>
    <FunctionName>public void SetDirectoryPath(string DirectoryPath) =&gt; this.DirectoryPath = DirectoryPath</FunctionName>
    <NumberOfScopes>0</NumberOfScopes>
    <NumberOfLines>15</NumberOfLines>
  </Function>
  <Function>
    <FunctionName>public void SetFilesInDirectory(List&lt;string&gt; FilesWithFullPath)</FunctionName>
    <NumberOfScopes>0</NumberOfScopes>
    <NumberOfLines>19</NumberOfLines>
  </Function>
  <Function>
    <FunctionName>public string GetDirectoryPath()</FunctionName>
    <NumberOfScopes>0</NumberOfScopes>
    <NumberOfLines>21</NumberOfLines>
  </Function>
  <Function>
    <FunctionName>public string GetFilenameExtension()</FunctionName>
    <NumberOfScopes>0</NumberOfScopes>
    <NumberOfLines>23</NumberOfLines>
  </Function>
  <Function>
    <FunctionName>public void AddFileNamesToList(List&lt;string&gt; Files)</FunctionName>
    <NumberOfScopes>1</NumberOfScopes>
    <NumberOfLines>29</NumberOfLines>
  </Function>
  <Function>
    <FunctionName>static void Main(string[] args)</FunctionName>
    <NumberOfScopes>1</NumberOfScopes>
    <NumberOfLines>36</NumberOfLines>
  </Function>
  <Function>
    <FunctionName>public string GetFile() =&gt; file</FunctionName>
    <NumberOfScopes>0</NumberOfScopes>
    <NumberOfLines>3</NumberOfLines>
  </Function>
  <Function>
    <FunctionName>public void SetExtractedLines(string file) =&gt; AllExtractedLines = File.ReadAllLines(file).ToList&lt;string&gt;()</FunctionName>
    <NumberOfScopes>2</NumberOfScopes>
    <NumberOfLines>20</NumberOfLines>
  </Function>
  <Function>
    <FunctionName>public void SetFile(string file) =&gt; this.file = file</FunctionName>
    <NumberOfScopes>2</NumberOfScopes>
    <NumberOfLines>36</NumberOfLines>
  </Function>
  <Function>
    <FunctionName>private int FindPositionOfNamespace(List&lt;string&gt; list)</FunctionName>
    <NumberOfScopes>2</NumberOfScopes>
    <NumberOfLines>51</NumberOfLines>
  </Function>
  <Function>
    <FunctionName>/*public int CountStatements(List&lt;string&gt; lines)</FunctionName>
    <NumberOfScopes>2</NumberOfScopes>
    <NumberOfLines>61</NumberOfLines>
  </Function>
  <Function>
    <FunctionName>static void Main(string[] args)</FunctionName>
    <NumberOfScopes>0</NumberOfScopes>
    <NumberOfLines>63</NumberOfLines>
  </Function>
  <Function>
    <FunctionName>public void FindRelationships()</FunctionName>
    <NumberOfScopes>3</NumberOfScopes>
    <NumberOfLines>10</NumberOfLines>
  </Function>
  <Function>
    <FunctionName>public string GetClassName()</FunctionName>
    <NumberOfScopes>0</NumberOfScopes>
    <NumberOfLines>2</NumberOfLines>
  </Function>
  <Function>
    <FunctionName>public string GetFunctionName()</FunctionName>
    <NumberOfScopes>0</NumberOfScopes>
    <NumberOfLines>4</NumberOfLines>
  </Function>
  <Function>
    <FunctionName>public string GetNamespaceName()</FunctionName>
    <NumberOfScopes>0</NumberOfScopes>
    <NumberOfLines>6</NumberOfLines>
  </Function>
  <Function>
    <FunctionName>public int GetNumberOfScopes()</FunctionName>
    <NumberOfScopes>0</NumberOfScopes>
    <NumberOfLines>8</NumberOfLines>
  </Function>
  <Function>
    <FunctionName>public int GetNumberOfLines()</FunctionName>
    <NumberOfScopes>0</NumberOfScopes>
    <NumberOfLines>10</NumberOfLines>
  </Function>
  <Function>
    <FunctionName>public void SetNamespaceName(string namespaceName) =&gt; this.namespaceName = namespaceName</FunctionName>
    <NumberOfScopes>0</NumberOfScopes>
    <NumberOfLines>24</NumberOfLines>
  </Function>
  <Function>
    <FunctionName>public void SetClassName(string className) =&gt; this.className = className</FunctionName>
    <NumberOfScopes>0</NumberOfScopes>
    <NumberOfLines>37</NumberOfLines>
  </Function>
  <Function>
    <FunctionName>public void SetFunctionName(string functionName) =&gt; this.functionName = functionName</FunctionName>
    <NumberOfScopes>0</NumberOfScopes>
    <NumberOfLines>49</NumberOfLines>
  </Function>
  <Function>
    <FunctionName>public void SetNumberOfScopes(int numberOfScopes) =&gt; this.numberOfScopes = numberOfScopes</FunctionName>
    <NumberOfScopes>0</NumberOfScopes>
    <NumberOfLines>60</NumberOfLines>
  </Function>
  <Function>
    <FunctionName>public void SetNumberOfLines(int numberOfLines) =&gt; this.numberOfLines = numberOfLines</FunctionName>
    <NumberOfScopes>0</NumberOfScopes>
    <NumberOfLines>70</NumberOfLines>
  </Function>
  <Function>
    <FunctionName>public string GetScopeHead()</FunctionName>
    <NumberOfScopes>0</NumberOfScopes>
    <NumberOfLines>72</NumberOfLines>
  </Function>
  <Function>
    <FunctionName>public void SetScopeHead(string scopeHead) =&gt; this.scopeHead = scopeHead</FunctionName>
    <NumberOfScopes>0</NumberOfScopes>
    <NumberOfLines>75</NumberOfLines>
  </Function>
  <Function>
    <FunctionName>public void AddChild(ScopeNode sn) =&gt; children.Add(sn)</FunctionName>
    <NumberOfScopes>0</NumberOfScopes>
    <NumberOfLines>78</NumberOfLines>
  </Function>
  <Function>
    <FunctionName>public ScopeNode GetParent()</FunctionName>
    <NumberOfScopes>0</NumberOfScopes>
    <NumberOfLines>80</NumberOfLines>
  </Function>
  <Function>
    <FunctionName>public void SetParent(ScopeNode parent) =&gt; this.parent = parent</FunctionName>
    <NumberOfScopes>1</NumberOfScopes>
    <NumberOfLines>86</NumberOfLines>
  </Function>
  <Function>
    <FunctionName>public void PrintChildren()</FunctionName>
    <NumberOfScopes>1</NumberOfScopes>
    <NumberOfLines>91</NumberOfLines>
  </Function>
</Class>